voyagerpy/__init__.py
voyagerpy/_core/voyagerpy.py
voyagerpy/metrics/__init__.py
voyagerpy/metrics/metrics.py
voyagerpy/metrics/univariates.py
voyagerpy/plotting/__init__.py
voyagerpy/plotting/blues_colors.py
voyagerpy/plotting/cmap_helper.py
voyagerpy/plotting/ditto_colors.py
voyagerpy/plotting/plot.py
voyagerpy/plotting/rectangleplot.py
voyagerpy/plotting/roma_colors.py
voyagerpy/read.py
voyagerpy/spatial/__init__.py
voyagerpy/spatial/graphs.py
voyagerpy/spatial/spatial.py
voyagerpy/utils/__init__.py
voyagerpy/utils/hvg.py
voyagerpy/utils/markers.py
voyagerpy/utils/utils.py
voyagerpy-0.1.1.dist-info/METADATA
voyagerpy-0.1.1.dist-info/WHEEL
voyagerpy-0.1.1.dist-info/RECORD
