Metadata-Version: 2.1
Name: voyagerpy
Version: 0.1.1
Summary: Python library for Voyager, the geo-spatialist R library.
Home-page: https://pmelsted.github.io/voyagerpy
License: BSD-3-Clause
Keywords: Single-Cell,Spatial,voyager
Author: Pall Melsted
Author-email: pmelsted@hi.is
Requires-Python: >=3.8,<4
Classifier: License :: OSI Approved :: BSD License
Classifier: Programming Language :: Python :: 3
Classifier: Programming Language :: Python :: 3.8
Classifier: Programming Language :: Python :: 3.9
Classifier: Programming Language :: Python :: 3.10
Classifier: Programming Language :: Python :: 3.11
Provides-Extra: notebooks
Requires-Dist: anndata (>=0.8)
Requires-Dist: esda (>=2.4.3,<3.0.0)
Requires-Dist: fiona (>=1.9,<2.0)
Requires-Dist: geopandas (>=0.13,<0.14)
Requires-Dist: h5py (>=3.0,<4.0)
Requires-Dist: igraph (>=0.10.4) ; extra == "notebooks"
Requires-Dist: leidenalg (>=0.9.1,<0.10.0) ; extra == "notebooks"
Requires-Dist: libpysal (>=4.7.0,<5.0.0)
Requires-Dist: matplotlib (>=3.6,<3.7)
Requires-Dist: networkx (>=3.0)
Requires-Dist: numpy (>=1.22,<1.24)
Requires-Dist: opencv-python (>=4.7.0.72,<5.0.0.0)
Requires-Dist: pandas (>=1.3,<2.0)
Requires-Dist: scanpy (>=1.9.3,<2.0.0) ; extra == "notebooks"
Requires-Dist: scikit-learn (>=1.2)
Requires-Dist: scipy (>=1.10) ; python_version >= "3.8" and python_version < "3.12"
Requires-Dist: shapely (>=1.7)
Requires-Dist: statsmodels (>=0.13)
Project-URL: Bug Tracker, https://github.com/pmelsted/voyagerpy/issues
Project-URL: Repository, https://github.com/pmelsted/voyagerpy
